.DS_Store
pyvlog/__init__.py
pyvlog/converters.py
pyvlog/messagetypes.py
pyvlog/parsers.py
pyvlog/pyvlog.py
pyvlog/utils.py
pyvlog/tests/__init__.py
pyvlog/tests/test_pyvlog.py
pyvlog-0.1.dist-info/LICENSE
pyvlog-0.1.dist-info/METADATA
pyvlog-0.1.dist-info/WHEEL
pyvlog-0.1.dist-info/top_level.txt
pyvlog-0.1.dist-info/RECORD
