Metadata-Version: 2.1
Name: pyvlog
Version: 0.1
Summary: Python package for working with the V-Log traffic control data protocol
Home-page: https://github.com/HAL24K/pyvlog
Author: Samuel Blake
Author-email: samuelfblake@gmail.com
License: UNKNOWN
Platform: UNKNOWN
Classifier: Programming Language :: Python :: 3.7
Classifier: License :: OSI Approved :: GNU General Public License v3 (GPLv3)
Requires-Dist: ujson (>=1.35)
Requires-Dist: pandas (>=0.25.1)
